miru_server_sdk/__init__.py
miru_server_sdk/_base_client.py
miru_server_sdk/_client.py
miru_server_sdk/_compat.py
miru_server_sdk/_constants.py
miru_server_sdk/_exceptions.py
miru_server_sdk/_files.py
miru_server_sdk/_models.py
miru_server_sdk/_qs.py
miru_server_sdk/_resource.py
miru_server_sdk/_response.py
miru_server_sdk/_streaming.py
miru_server_sdk/_types.py
miru_server_sdk/_version.py
miru_server_sdk/py.typed
miru_server_sdk/_utils/__init__.py
miru_server_sdk/_utils/_compat.py
miru_server_sdk/_utils/_datetime_parse.py
miru_server_sdk/_utils/_logs.py
miru_server_sdk/_utils/_proxy.py
miru_server_sdk/_utils/_reflection.py
miru_server_sdk/_utils/_resources_proxy.py
miru_server_sdk/_utils/_streams.py
miru_server_sdk/_utils/_sync.py
miru_server_sdk/_utils/_transform.py
miru_server_sdk/_utils/_typing.py
miru_server_sdk/_utils/_utils.py
miru_server_sdk/lib/.keep
miru_server_sdk/resources/__init__.py
miru_server_sdk/resources/config_instances.py
miru_server_sdk/resources/deployments.py
miru_server_sdk/resources/devices.py
miru_server_sdk/resources/releases.py
miru_server_sdk/resources/webhooks.py
miru_server_sdk/types/__init__.py
miru_server_sdk/types/config_instance.py
miru_server_sdk/types/config_instance_list_params.py
miru_server_sdk/types/config_instance_list_response.py
miru_server_sdk/types/config_instance_retrieve_params.py
miru_server_sdk/types/config_schema.py
miru_server_sdk/types/config_type.py
miru_server_sdk/types/deployment.py
miru_server_sdk/types/deployment_create_params.py
miru_server_sdk/types/deployment_list_params.py
miru_server_sdk/types/deployment_list_response.py
miru_server_sdk/types/deployment_retrieve_params.py
miru_server_sdk/types/deployment_validate_params.py
miru_server_sdk/types/deployment_validate_response.py
miru_server_sdk/types/deployment_validate_webhook_event.py
miru_server_sdk/types/device.py
miru_server_sdk/types/device_create_activation_token_params.py
miru_server_sdk/types/device_create_activation_token_response.py
miru_server_sdk-0.6.1.dist-info/METADATA
miru_server_sdk-0.6.1.dist-info/WHEEL
miru_server_sdk-0.6.1.dist-info/licenses/LICENSE
miru_server_sdk-0.6.1.dist-info/RECORD
